sagemagic/__init__.py
sagemagic/eight_queens_genetic.py
sagemagic/logic_and_bayes.py
sagemagic/tsp_genetic.py
sagemagic-0.1.0.dist-info/licenses/LICENSE
sagemagic-0.1.0.dist-info/METADATA
sagemagic-0.1.0.dist-info/WHEEL
sagemagic-0.1.0.dist-info/top_level.txt
sagemagic-0.1.0.dist-info/RECORD
