Metadata-Version: 2.4
Name: sagemagic
Version: 0.1.0
Summary: AI algorithms collection: Genetic algorithms for 8-Queens and TSP, plus propositional logic and Bayes theorem implementations
Home-page: https://github.com/yourusername/sagemagic
Author: Your Name
Author-email: Your Name <your.email@example.com>
Project-URL: Homepage, https://github.com/yourusername/sagemagic
Project-URL: Bug Reports, https://github.com/yourusername/sagemagic/issues
Project-URL: Source, https://github.com/yourusername/sagemagic
Keywords: genetic-algorithm,artificial-intelligence,8-queens,tsp,traveling-salesman,propositional-logic,bayes-theorem,machine-learning
Classifier: Development Status :: 3 - Alpha
Classifier: Intended Audience :: Education
Classifier: Intended Audience :: Developers
Classifier: License :: OSI Approved :: MIT License
Classifier: Operating System :: OS Independent
Classifier: Programming Language :: Python :: 3
Classifier: Programming Language :: Python :: 3.7
Classifier: Programming Language :: Python :: 3.8
Classifier: Programming Language :: Python :: 3.9
Classifier: Programming Language :: Python :: 3.10
Classifier: Programming Language :: Python :: 3.11
Classifier: Topic :: Scientific/Engineering :: Artificial Intelligence
Classifier: Topic :: Education
Classifier: Topic :: Software Development :: Libraries :: Python Modules
Requires-Python: >=3.7
License-File: LICENSE
Requires-Dist: random2>=1.0.1
Dynamic: author
Dynamic: home-page
Dynamic: license-file
Dynamic: requires-python
